README.md
setup.py
keypendium/__init__.py
keypendium/keypendium.py
keypendium/test.py
keypendium.egg-info/PKG-INFO
keypendium.egg-info/SOURCES.txt
keypendium.egg-info/dependency_links.txt
keypendium.egg-info/top_level.txt