Metadata-Version: 1.0
Name: keypendium
Version: 0.1.9
Summary: A Wrapper for the keyforge-compendium.com API
Home-page: UNKNOWN
Author: caerulius
Author-email: cae@polywhack.com
License: UNKNOWN
Platform: UNKNOWN
